requestChecker/MethodsEnum.py
requestChecker/Path.py
requestChecker/RequestChecker.py
requestChecker/SecurityPolicyEnum.py
requestChecker/__init__.py
requestChecker-0.0.1.dist-info/DESCRIPTION.rst
requestChecker-0.0.1.dist-info/METADATA
requestChecker-0.0.1.dist-info/RECORD
requestChecker-0.0.1.dist-info/WHEEL
requestChecker-0.0.1.dist-info/metadata.json
requestChecker-0.0.1.dist-info/top_level.txt
