Metadata-Version: 2.0
Name: requestChecker
Version: 0.0.1
Summary: "Flask module allowing to configure and centralize the authorizations on the routes"
Home-page: https://github.com/vincauddu29/phypster
License: GNU GPLv3
Keywords: flask,security,url
Platform: UNKNOWN
Classifier: Programming Language :: Python :: 3
Classifier: License :: OSI Approved :: MIT License
Classifier: Operating System :: OS Independent
Requires-Python: >=3.6
Requires-Dist: Flask (==1.1.2)
Requires-Dist: Flask-RESTful (==0.3.8)
Requires-Dist: Flask-JWT-Extended (==3.25.0)
